jsgf/__init__.py
jsgf/errors.py
jsgf/expansions.py
jsgf/grammars.py
jsgf/parser.py
jsgf/references.py
jsgf/rules.py
jsgf/ext/__init__.py
jsgf/ext/expansions.py
jsgf/ext/grammars.py
jsgf/ext/rules.py
test/__init__.py
test/test_expansions.py
test/test_ext_expansions.py
test/test_ext_grammars.py
test/test_ext_rules.py
test/test_generators.py
test/test_grammars.py
test/test_importing.py
test/test_matches.py
test/test_parser.py
test/test_rules.py
pyjsgf-1.9.0.dist-info/LICENSE
pyjsgf-1.9.0.dist-info/METADATA
pyjsgf-1.9.0.dist-info/WHEEL
pyjsgf-1.9.0.dist-info/top_level.txt
pyjsgf-1.9.0.dist-info/RECORD
